screw_detector/__init__.py
screw_detector/complete_pipeline_parts.py
screw_detector/config.py
screw_detector/dataset.py
screw_detector/inference.py
screw_detector/models.py
screw_detector/sahi_utils.py
screw_detector/utils.py
screw_detector-0.1.0.dist-info/licenses/LICENSE
scripts/demo.py
scripts/evaluate.py
scripts/export.py
scripts/slice_dataset.py
scripts/train.py
screw_detector-0.1.0.dist-info/METADATA
screw_detector-0.1.0.dist-info/WHEEL
screw_detector-0.1.0.dist-info/entry_points.txt
screw_detector-0.1.0.dist-info/top_level.txt
screw_detector-0.1.0.dist-info/RECORD
