Metadata-Version: 2.4
Name: screw-detector
Version: 0.1.0
Summary: YOLOv8 + SAHI Detection Pipeline for Tiny Object Optimization
Author-email: Screw Detector Team <3bsalam0@gmail.com>
License: MIT
Project-URL: Homepage, https://github.com/3bsalam-1/Screw-Detector
Project-URL: Documentation, https://github.com/3bsalam-1/Screw-Detector#readme
Project-URL: Repository, https://github.com/3bsalam-1/Screw-Detector
Project-URL: Bug Tracker, https://github.com/3bsalam-1/Screw-Detector/issues
Keywords: object-detection,yolo,sahi,computer-vision,deep-learning,tiny-objects,screw-detection
Classifier: Development Status :: 3 - Alpha
Classifier: Intended Audience :: Developers
Classifier: Intended Audience :: Science/Research
Classifier: License :: OSI Approved :: MIT License
Classifier: Operating System :: OS Independent
Classifier: Programming Language :: Python :: 3
Classifier: Programming Language :: Python :: 3.9
Classifier: Programming Language :: Python :: 3.10
Classifier: Programming Language :: Python :: 3.11
Classifier: Topic :: Scientific/Engineering :: Artificial Intelligence
Classifier: Topic :: Scientific/Engineering :: Image Recognition
Requires-Python: >=3.9
License-File: LICENSE
Requires-Dist: ultralytics>=8.4.0
Requires-Dist: sahi>=0.11.0
Requires-Dist: opencv-python>=4.8.0
Requires-Dist: pandas>=2.0.0
Requires-Dist: tqdm>=4.65.0
Requires-Dist: pyyaml>=6.0.0
Requires-Dist: matplotlib>=3.7.0
Requires-Dist: scipy>=1.10.0
Requires-Dist: seaborn>=0.12.0
Requires-Dist: psutil>=5.9.0
Requires-Dist: onnx>=1.14.0
Requires-Dist: onnxslim>=0.1.0
Requires-Dist: onnxruntime>=1.15.0
Requires-Dist: torch>=2.0.0
Requires-Dist: torchvision>=0.15.0
Requires-Dist: shapely>=2.0.0
Provides-Extra: dev
Requires-Dist: pytest>=7.4.0; extra == "dev"
Requires-Dist: pytest-cov>=4.1.0; extra == "dev"
Requires-Dist: ruff>=0.1.0; extra == "dev"
Requires-Dist: black>=23.7.0; extra == "dev"
Requires-Dist: mypy>=1.5.0; extra == "dev"
Requires-Dist: pre-commit>=3.5.0; extra == "dev"
Provides-Extra: notebook
Requires-Dist: jupyterlab>=4.0.0; extra == "notebook"
Requires-Dist: ipykernel>=6.25.0; extra == "notebook"
Dynamic: license-file
